setup.py
aria2/__init__.py
aria2/main.py
aria2/qrcode_test.py
aria2/controller/__init__.py
aria2/controller/aria2_api.py
aria2/controller/aria2_websocket.py
aria2/controller/mq_client.py
aria2Hello.egg-info/PKG-INFO
aria2Hello.egg-info/SOURCES.txt
aria2Hello.egg-info/dependency_links.txt
aria2Hello.egg-info/entry_points.txt
aria2Hello.egg-info/requires.txt
aria2Hello.egg-info/top_level.txt