Metadata-Version: 1.1
Name: aria2Hello
Version: 0.0.1.4
Summary: aria2Hello
Home-page: UNKNOWN
Author: Exception
Author-email: webmaster@pocketdigi.com
License: MIT
Keywords: aria2 wechat download
Platform: any
Classifier: Development Status :: 3 - Alpha
Classifier: Intended Audience :: Developers
Classifier: Topic :: Internet
Classifier: License :: Free For Home Use
Classifier: Programming Language :: Python :: 2.6
Classifier: Programming Language :: Python :: 2.7
